tgext/__init__.py
tgext/formencode/__init__.py
tgext/formencode/component.py
tgext/formencode/decorators.py
tgext/formencode/i18n.py
tgext_formencode-0.1.1.dist-info/licenses/LICENSE
tgext_formencode-0.1.1.dist-info/METADATA
tgext_formencode-0.1.1.dist-info/WHEEL
tgext_formencode-0.1.1.dist-info/top_level.txt
tgext_formencode-0.1.1.dist-info/RECORD
