Metadata-Version: 2.4
Name: tgext.formencode
Version: 0.1.1
Summary: Enable support for formencode validation library
Author-email: Alessandro Molina <amol@turbogears.org>
Keywords: turbogears2.extension
Requires-Python: >=3.7
License-File: LICENSE
Requires-Dist: TurboGears2>=2.5.0
Requires-Dist: formencode
Provides-Extra: testing
Requires-Dist: pytest; extra == "testing"
Requires-Dist: TurboGears2[testing]; extra == "testing"
Dynamic: license-file
